pose_openvr_wrapper/__init__.py
pose_openvr_wrapper/wrapper.py
pose_openvr_wrapper-0.1.4.data/data/pose_openvr_wrapper/config.json
pose_openvr_wrapper-0.1.4.dist-info/METADATA
pose_openvr_wrapper-0.1.4.dist-info/WHEEL
pose_openvr_wrapper-0.1.4.dist-info/top_level.txt
pose_openvr_wrapper-0.1.4.dist-info/RECORD
