Metadata-Version: 2.1
Name: pose-openvr-wrapper
Version: 0.1.4
Summary: PyOpenvr Library convenience wrapper for recovery of pose data
Home-page: https://github.com/virgileTN/pyopenvr_wrapper
Author: Virgile Daugé
Author-email: virgile.dauge@pm.me
License: UNKNOWN
Keywords: vive,tracking
Platform: UNKNOWN
Classifier: Development Status :: 4 - Beta
Classifier: Environment :: Console
Classifier: Intended Audience :: Developers
Classifier: License :: OSI Approved :: GNU General Public License (GPL)
Classifier: Operating System :: MacOS :: MacOS X
Classifier: Operating System :: Microsoft :: Windows
Classifier: Operating System :: POSIX
Classifier: Programming Language :: Python :: 2.7
Classifier: Programming Language :: Python :: 3.6
Requires-Dist: openvr (>=1.0.1701)
Requires-Dist: numpy (>=1.15.4)
